<?xml version="1.0" encoding="ISO-8859-1"?>
<Image>
    <Name>97.jpg</Name>
    <Class>conventional</Class>
    <Acquisition>1</Acquisition>
    <Plant>
        <Amount>12</Amount>
        <Distance>
            <Centimeters>35</Centimeters>
            <Centimeters>22</Centimeters>
            <Centimeters>29</Centimeters>
            <Centimeters>26</Centimeters>
            <Centimeters>27</Centimeters>
            <Centimeters>22</Centimeters>
            <Centimeters>35</Centimeters>
            <Centimeters>26</Centimeters>
            <Centimeters>25</Centimeters>
            <Centimeters>20</Centimeters>
            <Centimeters>23</Centimeters>
        </Distance>
        <Location>
            <Coordinates>
                <X>280</X>
                <Y>65</Y>
                <Width>133</Width>
                <Height>188</Height>
                <Center>
                    <X>333</X>
                    <Y>192</Y>
                    <Width>51</Width>
                    <Height>48</Height>
                </Center>
            </Coordinates>
            <Coordinates>
                <X>275</X>
                <Y>462</Y>
                <Width>186</Width>
                <Height>112</Height>
                <Center>
                    <X>350</X>
                    <Y>531</Y>
                    <Width>43</Width>
                    <Height>43</Height>
                </Center>
            </Coordinates>
            <Coordinates>
                <X>267</X>
                <Y>670</Y>
                <Width>145</Width>
                <Height>116</Height>
                <Center>
                    <X>346</X>
                    <Y>740</Y>
                    <Width>38</Width>
                    <Height>46</Height>
                </Center>
            </Coordinates>
            <Coordinates>
                <X>301</X>
                <Y>950</Y>
                <Width>113</Width>
                <Height>131</Height>
                <Center>
                    <X>363</X>
                    <Y>1016</Y>
                    <Width>46</Width>
                    <Height>65</Height>
                </Center>
            </Coordinates>
            <Coordinates>
                <X>301</X>
                <Y>1216</Y>
                <Width>145</Width>
                <Height>105</Height>
                <Center>
                    <X>358</X>
                    <Y>1283</Y>
                    <Width>39</Width>
                    <Height>38</Height>
                </Center>
            </Coordinates>
            <Coordinates>
                <X>301</X>
                <Y>1510</Y>
                <Width>165</Width>
                <Height>102</Height>
                <Center>
                    <X>366</X>
                    <Y>1568</Y>
                    <Width>49</Width>
                    <Height>44</Height>
                </Center>
            </Coordinates>
            <Coordinates>
                <X>304</X>
                <Y>1691</Y>
                <Width>124</Width>
                <Height>115</Height>
                <Center>
                    <X>345</X>
                    <Y>1764</Y>
                    <Width>60</Width>
                    <Height>42</Height>
                </Center>
            </Coordinates>
            <Coordinates>
                <X>272</X>
                <Y>2053</Y>
                <Width>147</Width>
                <Height>111</Height>
                <Center>
                    <X>335</X>
                    <Y>2113</Y>
                    <Width>53</Width>
                    <Height>51</Height>
                </Center>
            </Coordinates>
            <Coordinates>
                <X>308</X>
                <Y>2265</Y>
                <Width>115</Width>
                <Height>130</Height>
                <Center>
                    <X>332</X>
                    <Y>2362</Y>
                    <Width>55</Width>
                    <Height>33</Height>
                </Center>
            </Coordinates>
            <Coordinates>
                <X>299</X>
                <Y>2532</Y>
                <Width>156</Width>
                <Height>117</Height>
                <Center>
                    <X>349</X>
                    <Y>2601</Y>
                    <Width>57</Width>
                    <Height>48</Height>
                </Center>
            </Coordinates>
            <Coordinates>
                <X>300</X>
                <Y>2673</Y>
                <Width>138</Width>
                <Height>167</Height>
                <Center>
                    <X>352</X>
                    <Y>2784</Y>
                    <Width>59</Width>
                    <Height>56</Height>
                </Center>
            </Coordinates>
            <Coordinates>
                <X>268</X>
                <Y>2897</Y>
                <Width>165</Width>
                <Height>158</Height>
                <Center>
                    <X>353</X>
                    <Y>3009</Y>
                    <Width>48</Width>
                    <Height>43</Height>
                </Center>
            </Coordinates>
        </Location>
    </Plant>
</Image>
