<?xml version="1.0" encoding="ISO-8859-1"?>
<Image>
    <Name>98.jpg</Name>
    <Class>conventional</Class>
    <Acquisition>1.04</Acquisition>
    <Plant>
        <Amount>12</Amount>
        <Distance>
            <Centimeters>28</Centimeters>
            <Centimeters>23</Centimeters>
            <Centimeters>27</Centimeters>
            <Centimeters>23</Centimeters>
            <Centimeters>29</Centimeters>
            <Centimeters>24</Centimeters>
            <Centimeters>29</Centimeters>
            <Centimeters>27</Centimeters>
            <Centimeters>24</Centimeters>
            <Centimeters>23</Centimeters>
            <Centimeters>30</Centimeters>
        </Distance>
        <Location>
            <Coordinates>
                <X>282</X>
                <Y>96</Y>
                <Width>145</Width>
                <Height>143</Height>
                <Center>
                    <X>334</X>
                    <Y>181</Y>
                    <Width>58</Width>
                    <Height>58</Height>
                </Center>
            </Coordinates>
            <Coordinates>
                <X>253</X>
                <Y>375</Y>
                <Width>141</Width>
                <Height>131</Height>
                <Center>
                    <X>314</X>
                    <Y>461</Y>
                    <Width>57</Width>
                    <Height>45</Height>
                </Center>
            </Coordinates>
            <Coordinates>
                <X>290</X>
                <Y>573</Y>
                <Width>145</Width>
                <Height>183</Height>
                <Center>
                    <X>316</X>
                    <Y>680</Y>
                    <Width>49</Width>
                    <Height>61</Height>
                </Center>
            </Coordinates>
            <Coordinates>
                <X>243</X>
                <Y>893</Y>
                <Width>157</Width>
                <Height>104</Height>
                <Center>
                    <X>307</X>
                    <Y>963</Y>
                    <Width>58</Width>
                    <Height>34</Height>
                </Center>
            </Coordinates>
            <Coordinates>
                <X>245</X>
                <Y>1090</Y>
                <Width>181</Width>
                <Height>119</Height>
                <Center>
                    <X>316</X>
                    <Y>1158</Y>
                    <Width>50</Width>
                    <Height>51</Height>
                </Center>
            </Coordinates>
            <Coordinates>
                <X>285</X>
                <Y>1371</Y>
                <Width>145</Width>
                <Height>129</Height>
                <Center>
                    <X>316</X>
                    <Y>1457</Y>
                    <Width>48</Width>
                    <Height>43</Height>
                </Center>
            </Coordinates>
            <Coordinates>
                <X>266</X>
                <Y>1623</Y>
                <Width>119</Width>
                <Height>133</Height>
                <Center>
                    <X>330</X>
                    <Y>1704</Y>
                    <Width>40</Width>
                    <Height>52</Height>
                </Center>
            </Coordinates>
            <Coordinates>
                <X>288</X>
                <Y>1887</Y>
                <Width>118</Width>
                <Height>133</Height>
                <Center>
                    <X>336</X>
                    <Y>1970</Y>
                    <Width>46</Width>
                    <Height>50</Height>
                </Center>
            </Coordinates>
            <Coordinates>
                <X>300</X>
                <Y>2142</Y>
                <Width>169</Width>
                <Height>144</Height>
                <Center>
                    <X>335</X>
                    <Y>2236</Y>
                    <Width>65</Width>
                    <Height>50</Height>
                </Center>
            </Coordinates>
            <Coordinates>
                <X>277</X>
                <Y>2393</Y>
                <Width>170</Width>
                <Height>126</Height>
                <Center>
                    <X>350</X>
                    <Y>2479</Y>
                    <Width>49</Width>
                    <Height>40</Height>
                </Center>
            </Coordinates>
            <Coordinates>
                <X>299</X>
                <Y>2631</Y>
                <Width>150</Width>
                <Height>115</Height>
                <Center>
                    <X>356</X>
                    <Y>2692</Y>
                    <Width>47</Width>
                    <Height>54</Height>
                </Center>
            </Coordinates>
            <Coordinates>
                <X>299</X>
                <Y>2911</Y>
                <Width>155</Width>
                <Height>171</Height>
                <Center>
                    <X>370</X>
                    <Y>3008</Y>
                    <Width>50</Width>
                    <Height>45</Height>
                </Center>
            </Coordinates>
        </Location>
    </Plant>
</Image>
